odoo/addons/purchase_stock_picking_restrict_cancel/README.rst
odoo/addons/purchase_stock_picking_restrict_cancel/__init__.py
odoo/addons/purchase_stock_picking_restrict_cancel/__manifest__.py
odoo/addons/purchase_stock_picking_restrict_cancel/i18n/it.po
odoo/addons/purchase_stock_picking_restrict_cancel/i18n/pt_BR.po
odoo/addons/purchase_stock_picking_restrict_cancel/i18n/purchase_stock_picking_restrict_cancel.pot
odoo/addons/purchase_stock_picking_restrict_cancel/models/__init__.py
odoo/addons/purchase_stock_picking_restrict_cancel/models/stock_move.py
odoo/addons/purchase_stock_picking_restrict_cancel/readme/CONTRIBUTORS.rst
odoo/addons/purchase_stock_picking_restrict_cancel/readme/DESCRIPTION.rst
odoo/addons/purchase_stock_picking_restrict_cancel/static/description/icon.png
odoo/addons/purchase_stock_picking_restrict_cancel/static/description/index.html
odoo/addons/purchase_stock_picking_restrict_cancel/tests/__init__.py
odoo/addons/purchase_stock_picking_restrict_cancel/tests/test_purchase_picking_restrict_cancel.py
odoo12_addon_purchase_stock_picking_restrict_cancel-12.0.1.0.0.99.dev9.dist-info/METADATA
odoo12_addon_purchase_stock_picking_restrict_cancel-12.0.1.0.0.99.dev9.dist-info/WHEEL
odoo12_addon_purchase_stock_picking_restrict_cancel-12.0.1.0.0.99.dev9.dist-info/top_level.txt
odoo12_addon_purchase_stock_picking_restrict_cancel-12.0.1.0.0.99.dev9.dist-info/RECORD
